[
  {
    "id": "203d794a-a9c7-49f1-a082-6649ddd22bb6",
    "title": null,
    "content": "사실 주인공이 불치병",
    "score": 5,
    "createdAt": "2023-04-27T15:20:32.940Z",
    "updatedAt": "2023-04-27T15:22:57.017Z",
    "user": {
      "id": "daf1a6b6-0f7a-46a3-b9c4-b18da4ce33b9",
      "name": "김불닭",
      "email": "dak@email.com",
      "gender": null,
      "nickname": "닭발",
      "description": "무뼈닭발에 주먹밥 먹으면 엄청 맛있다구요 진짜로!",
      "createdAt": "2023-04-27T02:25:44.086Z",
      "updatedAt": "2023-05-26T13:33:56.493Z",
      "isPublic": true,
      "isLikeView": true,
      "isReviewView": true,
      "isPreferenceView": true,
      "birth": "19970320",
      "profileImage": "ImageProfile3"
    },
    "comments": [
      {
        "id": "21c4c9b4-a172-46ee-b27a-8584b9dca934",
        "content": "헉 스포당했다 !!",
        "createdAt": "2023-05-05T11:02:15.334Z",
        "updatedAt": "2023-05-05T11:02:15.334Z",
        "user": {
          "id": "c070a168-80e9-4915-baa4-52ca50ba7645",
          "name": "셀렉터 1조",
          "email": "gm@gm.com",
          "gender": null,
          "nickname": "렉터터터",
          "description": "안녕하세요 1조 \"무비셀렉터\" 입니다.\n잘 부탁드립니다!",
          "createdAt": "2023-04-25T03:22:29.108Z",
          "updatedAt": "2023-04-28T01:12:22.967Z",
          "isPublic": true,
          "isLikeView": true,
          "isReviewView": true,
          "isPreferenceView": true,
          "birth": "111111",
          "profileImage": null
        }
      }
    ],
    "likeCount": 2,
    "hateCount": 0,
    "isLiked": false,
    "isHated": false,
    "enjoyPoints": ["연기", "스토리"],
    "tensions": ["낮음"],
    "movie": {
      "id": "368cba63-14da-4987-80ed-a9de81566688",
      "title": " 소년을 위로해줘!",
      "postImage": "http://file.koreafilm.or.kr/thm/02/99/17/79/tn_DPK019466.jpg",
      "plot": "양궁 선수를 끔꾸며 앞만 보고 달려오던 다열이, 과거의 상처로 감정을 속이게 된 태현과 마주치다.체육 특기생으로 양궁 훈련 받는 고등학생 다열은 양궁을 시작한 초등학교 때부터 다른 길은 생각하지 못한 채 살아왔다. 하지만 지는 게 두려워 활을 놓지 못하는 그에게 양궁은 두려움이다. 어느 날 다열이 보건실에서 같은 반 태현이 친구와 장난치는 모습을 연인이라고 오해하며 놀라는 바람에 침대 사이 커튼을 무너뜨리고 태현의 위로 넘어진다. 그 순간 보건 선생님이 들어오자 태현은 다열에게 다짜고짜 누명을 씌우는데.. 졸지에 변태로 찍혀버린 다열이 태현에게 따지지만 죄책감을 느끼기는 커녕 계속 장난을 치며 자신을 괴롭히는 태현을 이해할 수 없다. 그렇게 서로를 데면데면하게 지내던 어느 날. 다열은 태현의 이모가 학교에 찾아와 태현에게 살인자라며 화를 내는 모습을 보게 된다. 폭언을 듣고도 동요 없이, 자기가 죽으면 해결되는 거냐고 덤덤히 답하는 태현. 겉으로는 차가운 표정과 감정이 없어 보이는 태현이지만 혼자 사는 태현의 집 베개에 남은 눈물 자국... 태현은 과거에 무슨 일을 겪은 걸까? 한편 다열은 자신이 왜 양궁을 해야 하는지 목적을 찾지 못한 채 점점 집중하지 못하게 된다.",
      "releasedAt": "20220908",
      "runtime": "88",
      "company": "㈜픽쳐레스크,엠오디티",
      "averageScore": 3.75,
      "genres": [
        {
          "id": "73fa7e1d-0e3e-4506-9432-21c29faa8dd7",
          "name": "멜로/로맨스"
        },
        {
          "id": "7d663bf1-14fe-4320-b409-7d70ddd21560",
          "name": "드라마"
        }
      ]
    }
  },
  {
    "id": "2bb838f9-b5ed-4fe8-831f-8b66da969f2c",
    "title": null,
    "content": " 재밌어요 강추!",
    "score": 4,
    "createdAt": "2023-04-26T02:25:09.699Z",
    "updatedAt": "2023-04-26T02:25:09.699Z",
    "user": {
      "id": "84bc94e2-1f7a-47cb-a1ed-b8bf1cd3c2ca",
      "name": "김나임",
      "email": "test@email.com",
      "gender": null,
      "nickname": "박박찐만두",
      "description": "안녕하세요!",
      "createdAt": "2023-04-25T21:39:35.809Z",
      "updatedAt": "2023-04-26T05:53:31.668Z",
      "isPublic": false,
      "isLikeView": true,
      "isReviewView": true,
      "isPreferenceView": true,
      "birth": "19970924",
      "profileImage": "ImageProfile8"
    },
    "comments": [],
    "likeCount": 1,
    "hateCount": 1,
    "isLiked": false,
    "isHated": false,
    "enjoyPoints": ["연기"],
    "tensions": ["낮음"],
    "movie": {
      "id": "368cba63-14da-4987-80ed-a9de81566688",
      "title": " 소년을 위로해줘!",
      "postImage": "http://file.koreafilm.or.kr/thm/02/99/17/79/tn_DPK019466.jpg",
      "plot": "양궁 선수를 끔꾸며 앞만 보고 달려오던 다열이, 과거의 상처로 감정을 속이게 된 태현과 마주치다.체육 특기생으로 양궁 훈련 받는 고등학생 다열은 양궁을 시작한 초등학교 때부터 다른 길은 생각하지 못한 채 살아왔다. 하지만 지는 게 두려워 활을 놓지 못하는 그에게 양궁은 두려움이다. 어느 날 다열이 보건실에서 같은 반 태현이 친구와 장난치는 모습을 연인이라고 오해하며 놀라는 바람에 침대 사이 커튼을 무너뜨리고 태현의 위로 넘어진다. 그 순간 보건 선생님이 들어오자 태현은 다열에게 다짜고짜 누명을 씌우는데.. 졸지에 변태로 찍혀버린 다열이 태현에게 따지지만 죄책감을 느끼기는 커녕 계속 장난을 치며 자신을 괴롭히는 태현을 이해할 수 없다. 그렇게 서로를 데면데면하게 지내던 어느 날. 다열은 태현의 이모가 학교에 찾아와 태현에게 살인자라며 화를 내는 모습을 보게 된다. 폭언을 듣고도 동요 없이, 자기가 죽으면 해결되는 거냐고 덤덤히 답하는 태현. 겉으로는 차가운 표정과 감정이 없어 보이는 태현이지만 혼자 사는 태현의 집 베개에 남은 눈물 자국... 태현은 과거에 무슨 일을 겪은 걸까? 한편 다열은 자신이 왜 양궁을 해야 하는지 목적을 찾지 못한 채 점점 집중하지 못하게 된다.",
      "releasedAt": "20220908",
      "runtime": "88",
      "company": "㈜픽쳐레스크,엠오디티",
      "averageScore": 3.75,
      "genres": [
        {
          "id": "73fa7e1d-0e3e-4506-9432-21c29faa8dd7",
          "name": "멜로/로맨스"
        },
        {
          "id": "7d663bf1-14fe-4320-b409-7d70ddd21560",
          "name": "드라마"
        }
      ]
    }
  },
  {
    "id": "35034d22-4a85-4d24-99d0-785a2b0f4b30",
    "title": null,
    "content": "위로해줘!",
    "score": 3.5,
    "createdAt": "2023-04-25T16:28:59.543Z",
    "updatedAt": "2023-04-25T16:29:06.220Z",
    "user": {
      "id": "b3ff022e-e5e7-40b9-9a49-337814f9a712",
      "name": "임신영",
      "email": "sy1001@naver.com",
      "gender": null,
      "nickname": "신영!",
      "description": "신영이야",
      "createdAt": "2023-04-25T16:27:12.677Z",
      "updatedAt": "2023-04-25T16:30:26.936Z",
      "isPublic": true,
      "isLikeView": false,
      "isReviewView": false,
      "isPreferenceView": true,
      "birth": null,
      "profileImage": "AssasinIcon"
    },
    "comments": [],
    "likeCount": 0,
    "hateCount": 0,
    "isLiked": false,
    "isHated": false,
    "enjoyPoints": [],
    "tensions": [],
    "movie": {
      "id": "368cba63-14da-4987-80ed-a9de81566688",
      "title": " 소년을 위로해줘!",
      "postImage": "http://file.koreafilm.or.kr/thm/02/99/17/79/tn_DPK019466.jpg",
      "plot": "양궁 선수를 끔꾸며 앞만 보고 달려오던 다열이, 과거의 상처로 감정을 속이게 된 태현과 마주치다.체육 특기생으로 양궁 훈련 받는 고등학생 다열은 양궁을 시작한 초등학교 때부터 다른 길은 생각하지 못한 채 살아왔다. 하지만 지는 게 두려워 활을 놓지 못하는 그에게 양궁은 두려움이다. 어느 날 다열이 보건실에서 같은 반 태현이 친구와 장난치는 모습을 연인이라고 오해하며 놀라는 바람에 침대 사이 커튼을 무너뜨리고 태현의 위로 넘어진다. 그 순간 보건 선생님이 들어오자 태현은 다열에게 다짜고짜 누명을 씌우는데.. 졸지에 변태로 찍혀버린 다열이 태현에게 따지지만 죄책감을 느끼기는 커녕 계속 장난을 치며 자신을 괴롭히는 태현을 이해할 수 없다. 그렇게 서로를 데면데면하게 지내던 어느 날. 다열은 태현의 이모가 학교에 찾아와 태현에게 살인자라며 화를 내는 모습을 보게 된다. 폭언을 듣고도 동요 없이, 자기가 죽으면 해결되는 거냐고 덤덤히 답하는 태현. 겉으로는 차가운 표정과 감정이 없어 보이는 태현이지만 혼자 사는 태현의 집 베개에 남은 눈물 자국... 태현은 과거에 무슨 일을 겪은 걸까? 한편 다열은 자신이 왜 양궁을 해야 하는지 목적을 찾지 못한 채 점점 집중하지 못하게 된다.",
      "releasedAt": "20220908",
      "runtime": "88",
      "company": "㈜픽쳐레스크,엠오디티",
      "averageScore": 3.75,
      "genres": [
        {
          "id": "73fa7e1d-0e3e-4506-9432-21c29faa8dd7",
          "name": "멜로/로맨스"
        },
        {
          "id": "7d663bf1-14fe-4320-b409-7d70ddd21560",
          "name": "드라마"
        }
      ]
    }
  },
  {
    "id": "432aa620-45f1-470c-b103-1e948c65aa66",
    "title": null,
    "content": "오늘 ㅎㅏ루만➫ ❧♔튺7ㅏ!\n❦온ㅏ벽한✏♕ 코띵 ✿❦실력을✰ 윍핹 투ㅈㅏ핤ㅅㅔ욡!½\n\n7H발찷 ㅇㅓ๑ε♞렵௨ㅈㅣ♂ 않ㅇㅏ요❀➴!\n\n010❀-✣ＸＸＸＸ❥☞-ＸＸＸＸ➙",
    "score": 1,
    "createdAt": "2023-04-25T23:40:16.541Z",
    "updatedAt": "2023-04-25T23:40:16.541Z",
    "user": {
      "id": "9566ca93-d408-4a28-be56-05d36b0f36c0",
      "name": "김나임",
      "email": "test1@aa.aa",
      "gender": null,
      "nickname": "박박군만두",
      "description": "안녕!",
      "createdAt": "2023-04-25T23:18:08.791Z",
      "updatedAt": "2023-04-25T23:20:20.272Z",
      "isPublic": true,
      "isLikeView": true,
      "isReviewView": true,
      "isPreferenceView": true,
      "birth": "19970924",
      "profileImage": "ImageProfile6"
    },
    "comments": [
      {
        "id": "c8a18ab8-7351-4722-9a84-11339d8531ce",
        "content": "무슨 말인지 모르겠어요 ㅠㅠ",
        "createdAt": "2023-08-08T07:37:25.105Z",
        "updatedAt": "2023-08-08T07:37:25.105Z",
        "user": {
          "id": "3f5f0ac5-d2c4-464c-b0a4-a428d62aab60",
          "name": "주양아",
          "email": "yy@yy.com",
          "gender": null,
          "nickname": "양",
          "description": null,
          "createdAt": "2023-07-22T11:32:38.566Z",
          "updatedAt": "2023-07-22T11:32:38.566Z",
          "isPublic": true,
          "isLikeView": true,
          "isReviewView": true,
          "isPreferenceView": true,
          "birth": "970409",
          "profileImage": null
        }
      },
      {
        "id": "2e8ec16c-e79e-4e81-a69c-81882d2b1f71",
        "content": "whgdk",
        "createdAt": "2023-04-27T05:38:02.302Z",
        "updatedAt": "2023-04-27T05:38:02.302Z",
        "user": {
          "id": "f2a54aad-37c5-4c53-af53-6c22e63111e1",
          "name": "렉터",
          "email": "admin@a.com",
          "gender": null,
          "nickname": "터터",
          "description": "반가워요~~sdfsdf",
          "createdAt": "2023-04-25T03:55:35.161Z",
          "updatedAt": "2023-04-27T03:43:06.586Z",
          "isPublic": true,
          "isLikeView": true,
          "isReviewView": true,
          "isPreferenceView": true,
          "birth": "111111",
          "profileImage": null
        }
      },
      {
        "id": "8fd86f1e-5cf3-4056-b6e1-4741f84f39d0",
        "content": "영화가 얼마나 충격적이면 ㄷㄷ",
        "createdAt": "2023-04-26T02:55:25.548Z",
        "updatedAt": "2023-04-26T02:55:25.548Z",
        "user": {
          "id": "b5fb8a30-0302-4dde-aae6-311153e2caf8",
          "name": "admin",
          "email": "admin1@a.com",
          "gender": null,
          "nickname": "admin",
          "description": "admin2",
          "createdAt": "2023-04-25T05:09:59.125Z",
          "updatedAt": "2023-04-27T03:40:13.354Z",
          "isPublic": true,
          "isLikeView": true,
          "isReviewView": true,
          "isPreferenceView": true,
          "birth": "000000",
          "profileImage": null
        }
      }
    ],
    "likeCount": 0,
    "hateCount": 2,
    "isLiked": false,
    "isHated": false,
    "enjoyPoints": ["연기"],
    "tensions": ["낮음"],
    "movie": {
      "id": "368cba63-14da-4987-80ed-a9de81566688",
      "title": " 소년을 위로해줘!",
      "postImage": "http://file.koreafilm.or.kr/thm/02/99/17/79/tn_DPK019466.jpg",
      "plot": "양궁 선수를 끔꾸며 앞만 보고 달려오던 다열이, 과거의 상처로 감정을 속이게 된 태현과 마주치다.체육 특기생으로 양궁 훈련 받는 고등학생 다열은 양궁을 시작한 초등학교 때부터 다른 길은 생각하지 못한 채 살아왔다. 하지만 지는 게 두려워 활을 놓지 못하는 그에게 양궁은 두려움이다. 어느 날 다열이 보건실에서 같은 반 태현이 친구와 장난치는 모습을 연인이라고 오해하며 놀라는 바람에 침대 사이 커튼을 무너뜨리고 태현의 위로 넘어진다. 그 순간 보건 선생님이 들어오자 태현은 다열에게 다짜고짜 누명을 씌우는데.. 졸지에 변태로 찍혀버린 다열이 태현에게 따지지만 죄책감을 느끼기는 커녕 계속 장난을 치며 자신을 괴롭히는 태현을 이해할 수 없다. 그렇게 서로를 데면데면하게 지내던 어느 날. 다열은 태현의 이모가 학교에 찾아와 태현에게 살인자라며 화를 내는 모습을 보게 된다. 폭언을 듣고도 동요 없이, 자기가 죽으면 해결되는 거냐고 덤덤히 답하는 태현. 겉으로는 차가운 표정과 감정이 없어 보이는 태현이지만 혼자 사는 태현의 집 베개에 남은 눈물 자국... 태현은 과거에 무슨 일을 겪은 걸까? 한편 다열은 자신이 왜 양궁을 해야 하는지 목적을 찾지 못한 채 점점 집중하지 못하게 된다.",
      "releasedAt": "20220908",
      "runtime": "88",
      "company": "㈜픽쳐레스크,엠오디티",
      "averageScore": 3.75,
      "genres": [
        {
          "id": "73fa7e1d-0e3e-4506-9432-21c29faa8dd7",
          "name": "멜로/로맨스"
        },
        {
          "id": "7d663bf1-14fe-4320-b409-7d70ddd21560",
          "name": "드라마"
        }
      ]
    }
  },
  {
    "id": "50d0dec9-e758-4417-893e-2e7b0c952c05",
    "title": null,
    "content": "대박영화",
    "score": 4,
    "createdAt": "2023-08-23T02:14:24.421Z",
    "updatedAt": "2023-08-24T09:03:30.567Z",
    "user": {
      "id": "bebee7fc-9e50-4359-b30a-2f08b2e399e6",
      "name": "김코딩",
      "email": "kang2781@naver.com",
      "gender": null,
      "nickname": "코코",
      "description": "호로로롱",
      "createdAt": "2023-08-23T02:13:36.469Z",
      "updatedAt": "2023-08-23T02:32:34.314Z",
      "isPublic": true,
      "isLikeView": true,
      "isReviewView": true,
      "isPreferenceView": true,
      "birth": "20000101",
      "profileImage": null
    },
    "comments": [],
    "likeCount": 0,
    "hateCount": 0,
    "isLiked": false,
    "isHated": false,
    "enjoyPoints": ["영상미"],
    "tensions": ["보통"],
    "movie": {
      "id": "368cba63-14da-4987-80ed-a9de81566688",
      "title": " 소년을 위로해줘!",
      "postImage": "http://file.koreafilm.or.kr/thm/02/99/17/79/tn_DPK019466.jpg",
      "plot": "양궁 선수를 끔꾸며 앞만 보고 달려오던 다열이, 과거의 상처로 감정을 속이게 된 태현과 마주치다.체육 특기생으로 양궁 훈련 받는 고등학생 다열은 양궁을 시작한 초등학교 때부터 다른 길은 생각하지 못한 채 살아왔다. 하지만 지는 게 두려워 활을 놓지 못하는 그에게 양궁은 두려움이다. 어느 날 다열이 보건실에서 같은 반 태현이 친구와 장난치는 모습을 연인이라고 오해하며 놀라는 바람에 침대 사이 커튼을 무너뜨리고 태현의 위로 넘어진다. 그 순간 보건 선생님이 들어오자 태현은 다열에게 다짜고짜 누명을 씌우는데.. 졸지에 변태로 찍혀버린 다열이 태현에게 따지지만 죄책감을 느끼기는 커녕 계속 장난을 치며 자신을 괴롭히는 태현을 이해할 수 없다. 그렇게 서로를 데면데면하게 지내던 어느 날. 다열은 태현의 이모가 학교에 찾아와 태현에게 살인자라며 화를 내는 모습을 보게 된다. 폭언을 듣고도 동요 없이, 자기가 죽으면 해결되는 거냐고 덤덤히 답하는 태현. 겉으로는 차가운 표정과 감정이 없어 보이는 태현이지만 혼자 사는 태현의 집 베개에 남은 눈물 자국... 태현은 과거에 무슨 일을 겪은 걸까? 한편 다열은 자신이 왜 양궁을 해야 하는지 목적을 찾지 못한 채 점점 집중하지 못하게 된다.",
      "releasedAt": "20220908",
      "runtime": "88",
      "company": "㈜픽쳐레스크,엠오디티",
      "averageScore": 3.75,
      "genres": [
        {
          "id": "73fa7e1d-0e3e-4506-9432-21c29faa8dd7",
          "name": "멜로/로맨스"
        },
        {
          "id": "7d663bf1-14fe-4320-b409-7d70ddd21560",
          "name": "드라마"
        }
      ]
    }
  },
  {
    "id": "6355adf9-6f34-4677-986b-0cc452abbf59",
    "title": null,
    "content": "진창에서 별을 올려다 본다는 것은",
    "score": 3,
    "createdAt": "2023-04-25T09:31:26.194Z",
    "updatedAt": "2023-04-25T09:31:26.194Z",
    "user": {
      "id": "94ba2b4d-c096-40c0-84fb-038723a1dc2e",
      "name": "강만두",
      "email": "mandu@email.com",
      "gender": null,
      "nickname": "이동진",
      "description": "안녕하세요 무빙진 입니다",
      "createdAt": "2023-04-25T08:44:10.647Z",
      "updatedAt": "2023-04-27T21:16:17.891Z",
      "isPublic": true,
      "isLikeView": true,
      "isReviewView": true,
      "isPreferenceView": true,
      "birth": "970924",
      "profileImage": "ImageProfile5"
    },
    "comments": [
      {
        "id": "b7f3669d-add8-48d6-9089-4c3eac82597e",
        "content": "짱!!",
        "createdAt": "2023-04-28T01:38:29.460Z",
        "updatedAt": "2023-04-28T01:38:29.460Z",
        "user": {
          "id": "7349e3e9-02cd-4e21-b141-6ba732f0d460",
          "name": "김만두",
          "email": "test@aa.aa",
          "gender": null,
          "nickname": "박박탕수육",
          "description": null,
          "createdAt": "2023-04-28T01:37:21.160Z",
          "updatedAt": "2023-04-28T01:39:42.446Z",
          "isPublic": false,
          "isLikeView": true,
          "isReviewView": true,
          "isPreferenceView": true,
          "birth": "19970924",
          "profileImage": "ImageProfile4"
        }
      },
      {
        "id": "995c4cfb-2d42-4103-b2fd-6fd7e67f5065",
        "content": "짱이에요!",
        "createdAt": "2023-04-27T03:06:33.209Z",
        "updatedAt": "2023-04-27T03:06:33.209Z",
        "user": {
          "id": "284c7dcb-b919-44f1-966b-6d79b88020fd",
          "name": "김나임테스트",
          "email": "naim@email.com",
          "gender": null,
          "nickname": "제가바뀌었어요",
          "description": "안녕하세요!!!",
          "createdAt": "2023-04-27T03:05:34.779Z",
          "updatedAt": "2023-04-27T03:07:57.577Z",
          "isPublic": false,
          "isLikeView": true,
          "isReviewView": true,
          "isPreferenceView": true,
          "birth": "19970924",
          "profileImage": "ImageProfile3"
        }
      },
      {
        "id": "05a057e1-32d4-4727-8436-956f6adff91f",
        "content": "짱!",
        "createdAt": "2023-04-26T00:40:09.965Z",
        "updatedAt": "2023-04-26T00:40:09.965Z",
        "user": {
          "id": "eef90b4b-afbb-466e-9c64-ef3a85699274",
          "name": "김테스트",
          "email": "test@gmail.com",
          "gender": null,
          "nickname": "김만두두두",
          "description": "안녕!",
          "createdAt": "2023-04-26T00:38:59.266Z",
          "updatedAt": "2023-04-26T00:41:11.667Z",
          "isPublic": true,
          "isLikeView": true,
          "isReviewView": true,
          "isPreferenceView": true,
          "birth": "19970924",
          "profileImage": "ImageProfile3"
        }
      },
      {
        "id": "9f6ac9b1-f63d-4b56-9c00-fb0f96e85f27",
        "content": "오 너무 좋은 말이에요",
        "createdAt": "2023-04-25T23:19:09.614Z",
        "updatedAt": "2023-04-25T23:19:09.614Z",
        "user": {
          "id": "9566ca93-d408-4a28-be56-05d36b0f36c0",
          "name": "김나임",
          "email": "test1@aa.aa",
          "gender": null,
          "nickname": "박박군만두",
          "description": "안녕!",
          "createdAt": "2023-04-25T23:18:08.791Z",
          "updatedAt": "2023-04-25T23:20:20.272Z",
          "isPublic": true,
          "isLikeView": true,
          "isReviewView": true,
          "isPreferenceView": true,
          "birth": "19970924",
          "profileImage": "ImageProfile6"
        }
      },
      {
        "id": "b826cd93-04e8-4656-8df7-31c6675b28a4",
        "content": "오 짱이에여!",
        "createdAt": "2023-04-25T21:40:29.805Z",
        "updatedAt": "2023-04-25T21:40:29.805Z",
        "user": {
          "id": "84bc94e2-1f7a-47cb-a1ed-b8bf1cd3c2ca",
          "name": "김나임",
          "email": "test@email.com",
          "gender": null,
          "nickname": "박박찐만두",
          "description": "안녕하세요!",
          "createdAt": "2023-04-25T21:39:35.809Z",
          "updatedAt": "2023-04-26T05:53:31.668Z",
          "isPublic": false,
          "isLikeView": true,
          "isReviewView": true,
          "isPreferenceView": true,
          "birth": "19970924",
          "profileImage": "ImageProfile8"
        }
      },
      {
        "id": "23e257ac-0da2-4e9e-98aa-5d06759b704f",
        "content": "역시 이동진 평론가님..",
        "createdAt": "2023-04-25T16:21:42.993Z",
        "updatedAt": "2023-04-25T16:21:42.993Z",
        "user": {
          "id": "ae9c24e2-5443-4417-99b1-527026267618",
          "name": "임신영",
          "email": "sy1002@naver.com",
          "gender": null,
          "nickname": "sy",
          "description": null,
          "createdAt": "2023-04-25T16:18:59.222Z",
          "updatedAt": "2023-04-25T16:25:19.914Z",
          "isPublic": true,
          "isLikeView": true,
          "isReviewView": true,
          "isPreferenceView": true,
          "birth": null,
          "profileImage": "CircusIcon"
        }
      }
    ],
    "likeCount": 8,
    "hateCount": 0,
    "isLiked": false,
    "isHated": false,
    "enjoyPoints": ["연기", "스토리"],
    "tensions": ["낮음"],
    "movie": {
      "id": "368cba63-14da-4987-80ed-a9de81566688",
      "title": " 소년을 위로해줘!",
      "postImage": "http://file.koreafilm.or.kr/thm/02/99/17/79/tn_DPK019466.jpg",
      "plot": "양궁 선수를 끔꾸며 앞만 보고 달려오던 다열이, 과거의 상처로 감정을 속이게 된 태현과 마주치다.체육 특기생으로 양궁 훈련 받는 고등학생 다열은 양궁을 시작한 초등학교 때부터 다른 길은 생각하지 못한 채 살아왔다. 하지만 지는 게 두려워 활을 놓지 못하는 그에게 양궁은 두려움이다. 어느 날 다열이 보건실에서 같은 반 태현이 친구와 장난치는 모습을 연인이라고 오해하며 놀라는 바람에 침대 사이 커튼을 무너뜨리고 태현의 위로 넘어진다. 그 순간 보건 선생님이 들어오자 태현은 다열에게 다짜고짜 누명을 씌우는데.. 졸지에 변태로 찍혀버린 다열이 태현에게 따지지만 죄책감을 느끼기는 커녕 계속 장난을 치며 자신을 괴롭히는 태현을 이해할 수 없다. 그렇게 서로를 데면데면하게 지내던 어느 날. 다열은 태현의 이모가 학교에 찾아와 태현에게 살인자라며 화를 내는 모습을 보게 된다. 폭언을 듣고도 동요 없이, 자기가 죽으면 해결되는 거냐고 덤덤히 답하는 태현. 겉으로는 차가운 표정과 감정이 없어 보이는 태현이지만 혼자 사는 태현의 집 베개에 남은 눈물 자국... 태현은 과거에 무슨 일을 겪은 걸까? 한편 다열은 자신이 왜 양궁을 해야 하는지 목적을 찾지 못한 채 점점 집중하지 못하게 된다.",
      "releasedAt": "20220908",
      "runtime": "88",
      "company": "㈜픽쳐레스크,엠오디티",
      "averageScore": 3.75,
      "genres": [
        {
          "id": "73fa7e1d-0e3e-4506-9432-21c29faa8dd7",
          "name": "멜로/로맨스"
        },
        {
          "id": "7d663bf1-14fe-4320-b409-7d70ddd21560",
          "name": "드라마"
        }
      ]
    }
  },
  {
    "id": "900a77f8-ad06-4513-a101-0bc5a9f88acc",
    "title": null,
    "content": "별점 4.5점 드립니다! 볼만한 영화에요~",
    "score": 4.5,
    "createdAt": "2023-05-05T11:01:19.448Z",
    "updatedAt": "2023-05-05T11:01:19.448Z",
    "user": {
      "id": "c070a168-80e9-4915-baa4-52ca50ba7645",
      "name": "셀렉터 1조",
      "email": "gm@gm.com",
      "gender": null,
      "nickname": "렉터터터",
      "description": "안녕하세요 1조 \"무비셀렉터\" 입니다.\n잘 부탁드립니다!",
      "createdAt": "2023-04-25T03:22:29.108Z",
      "updatedAt": "2023-04-28T01:12:22.967Z",
      "isPublic": true,
      "isLikeView": true,
      "isReviewView": true,
      "isPreferenceView": true,
      "birth": "111111",
      "profileImage": null
    },
    "comments": [],
    "likeCount": 2,
    "hateCount": 0,
    "isLiked": false,
    "isHated": false,
    "enjoyPoints": [],
    "tensions": [],
    "movie": {
      "id": "368cba63-14da-4987-80ed-a9de81566688",
      "title": " 소년을 위로해줘!",
      "postImage": "http://file.koreafilm.or.kr/thm/02/99/17/79/tn_DPK019466.jpg",
      "plot": "양궁 선수를 끔꾸며 앞만 보고 달려오던 다열이, 과거의 상처로 감정을 속이게 된 태현과 마주치다.체육 특기생으로 양궁 훈련 받는 고등학생 다열은 양궁을 시작한 초등학교 때부터 다른 길은 생각하지 못한 채 살아왔다. 하지만 지는 게 두려워 활을 놓지 못하는 그에게 양궁은 두려움이다. 어느 날 다열이 보건실에서 같은 반 태현이 친구와 장난치는 모습을 연인이라고 오해하며 놀라는 바람에 침대 사이 커튼을 무너뜨리고 태현의 위로 넘어진다. 그 순간 보건 선생님이 들어오자 태현은 다열에게 다짜고짜 누명을 씌우는데.. 졸지에 변태로 찍혀버린 다열이 태현에게 따지지만 죄책감을 느끼기는 커녕 계속 장난을 치며 자신을 괴롭히는 태현을 이해할 수 없다. 그렇게 서로를 데면데면하게 지내던 어느 날. 다열은 태현의 이모가 학교에 찾아와 태현에게 살인자라며 화를 내는 모습을 보게 된다. 폭언을 듣고도 동요 없이, 자기가 죽으면 해결되는 거냐고 덤덤히 답하는 태현. 겉으로는 차가운 표정과 감정이 없어 보이는 태현이지만 혼자 사는 태현의 집 베개에 남은 눈물 자국... 태현은 과거에 무슨 일을 겪은 걸까? 한편 다열은 자신이 왜 양궁을 해야 하는지 목적을 찾지 못한 채 점점 집중하지 못하게 된다.",
      "releasedAt": "20220908",
      "runtime": "88",
      "company": "㈜픽쳐레스크,엠오디티",
      "averageScore": 3.75,
      "genres": [
        {
          "id": "73fa7e1d-0e3e-4506-9432-21c29faa8dd7",
          "name": "멜로/로맨스"
        },
        {
          "id": "7d663bf1-14fe-4320-b409-7d70ddd21560",
          "name": "드라마"
        }
      ]
    }
  },
  {
    "id": "d837020c-b88b-4520-bf7b-983c16654663",
    "title": null,
    "content": "별점 5점드립니다~~~~~",
    "score": 5,
    "createdAt": "2023-08-05T13:08:59.106Z",
    "updatedAt": "2023-08-09T06:29:10.418Z",
    "user": {
      "id": "3f5f0ac5-d2c4-464c-b0a4-a428d62aab60",
      "name": "주양아",
      "email": "yy@yy.com",
      "gender": null,
      "nickname": "양",
      "description": null,
      "createdAt": "2023-07-22T11:32:38.566Z",
      "updatedAt": "2023-07-22T11:32:38.566Z",
      "isPublic": true,
      "isLikeView": true,
      "isReviewView": true,
      "isPreferenceView": true,
      "birth": "970409",
      "profileImage": null
    },
    "comments": [],
    "likeCount": 1,
    "hateCount": 0,
    "isLiked": false,
    "isHated": false,
    "enjoyPoints": [],
    "tensions": [],
    "movie": {
      "id": "368cba63-14da-4987-80ed-a9de81566688",
      "title": " 소년을 위로해줘!",
      "postImage": "http://file.koreafilm.or.kr/thm/02/99/17/79/tn_DPK019466.jpg",
      "plot": "양궁 선수를 끔꾸며 앞만 보고 달려오던 다열이, 과거의 상처로 감정을 속이게 된 태현과 마주치다.체육 특기생으로 양궁 훈련 받는 고등학생 다열은 양궁을 시작한 초등학교 때부터 다른 길은 생각하지 못한 채 살아왔다. 하지만 지는 게 두려워 활을 놓지 못하는 그에게 양궁은 두려움이다. 어느 날 다열이 보건실에서 같은 반 태현이 친구와 장난치는 모습을 연인이라고 오해하며 놀라는 바람에 침대 사이 커튼을 무너뜨리고 태현의 위로 넘어진다. 그 순간 보건 선생님이 들어오자 태현은 다열에게 다짜고짜 누명을 씌우는데.. 졸지에 변태로 찍혀버린 다열이 태현에게 따지지만 죄책감을 느끼기는 커녕 계속 장난을 치며 자신을 괴롭히는 태현을 이해할 수 없다. 그렇게 서로를 데면데면하게 지내던 어느 날. 다열은 태현의 이모가 학교에 찾아와 태현에게 살인자라며 화를 내는 모습을 보게 된다. 폭언을 듣고도 동요 없이, 자기가 죽으면 해결되는 거냐고 덤덤히 답하는 태현. 겉으로는 차가운 표정과 감정이 없어 보이는 태현이지만 혼자 사는 태현의 집 베개에 남은 눈물 자국... 태현은 과거에 무슨 일을 겪은 걸까? 한편 다열은 자신이 왜 양궁을 해야 하는지 목적을 찾지 못한 채 점점 집중하지 못하게 된다.",
      "releasedAt": "20220908",
      "runtime": "88",
      "company": "㈜픽쳐레스크,엠오디티",
      "averageScore": 3.75,
      "genres": [
        {
          "id": "73fa7e1d-0e3e-4506-9432-21c29faa8dd7",
          "name": "멜로/로맨스"
        },
        {
          "id": "7d663bf1-14fe-4320-b409-7d70ddd21560",
          "name": "드라마"
        }
      ]
    }
  }
]
